pyvaulter/__init__.py
pyvaulter-0.3.2.dist-info/METADATA
pyvaulter-0.3.2.dist-info/WHEEL
pyvaulter-0.3.2.dist-info/entry_points.txt
pyvaulter-0.3.2.dist-info/top_level.txt
pyvaulter-0.3.2.dist-info/RECORD
