Metadata-Version: 2.4
Name: pyvaulter
Version: 0.3.2
Summary: Encrypt sensitive data. Emulates much of the functionality of Ansible Vaults but for Python.
Author-email: kwilt <kwilt@pm.me>
Requires-Python: >=3.10
Requires-Dist: cryptography>=43.0.1
